<?xml version="1.0" encoding="UTF-8" standalone="yes"?>
<checkpoint>
    <version>
        3
    </version>
    <order>
        8
    </order>
    <level>
        255
    </level>
    <good_sequences>
        53
    </good_sequences>
    <solution>
        <sequence_accumulator>
            0
        </sequence_accumulator>
        <sequence_accumulator>
            1
        </sequence_accumulator>
        <sequence_accumulator>
            3
        </sequence_accumulator>
        <sequence_accumulator>
            2
        </sequence_accumulator>
        <sequence_accumulator>
            6
        </sequence_accumulator>
        <sequence_accumulator>
            4
        </sequence_accumulator>
        <sequence_accumulator>
            12
        </sequence_accumulator>
        <sequence_accumulator>
            8
        </sequence_accumulator>
        <sequence_accumulator>
            24
        </sequence_accumulator>
        <sequence_accumulator>
            16
        </sequence_accumulator>
        <sequence_accumulator>
            48
        </sequence_accumulator>
        <sequence_accumulator>
            32
        </sequence_accumulator>
        <sequence_accumulator>
            96
        </sequence_accumulator>
        <sequence_accumulator>
            64
        </sequence_accumulator>
        <sequence_accumulator>
            192
        </sequence_accumulator>
        <sequence_accumulator>
            128
        </sequence_accumulator>
        <sequence_accumulator>
            129
        </sequence_accumulator>
        <sequence_accumulator>
            131
        </sequence_accumulator>
        <sequence_accumulator>
            130
        </sequence_accumulator>
        <sequence_accumulator>
            134
        </sequence_accumulator>
        <sequence_accumulator>
            132
        </sequence_accumulator>
        <sequence_accumulator>
            133
        </sequence_accumulator>
        <sequence_accumulator>
            5
        </sequence_accumulator>
        <sequence_accumulator>
            13
        </sequence_accumulator>
        <sequence_accumulator>
            9
        </sequence_accumulator>
        <sequence_accumulator>
            11
        </sequence_accumulator>
        <sequence_accumulator>
            10
        </sequence_accumulator>
        <sequence_accumulator>
            26
        </sequence_accumulator>
        <sequence_accumulator>
            18
        </sequence_accumulator>
        <sequence_accumulator>
            19
        </sequence_accumulator>
        <sequence_accumulator>
            17
        </sequence_accumulator>
        <sequence_accumulator>
            21
        </sequence_accumulator>
        <sequence_accumulator>
            20
        </sequence_accumulator>
        <sequence_accumulator>
            52
        </sequence_accumulator>
        <sequence_accumulator>
            36
        </sequence_accumulator>
        <sequence_accumulator>
            37
        </sequence_accumulator>
        <sequence_accumulator>
            33
        </sequence_accumulator>
        <sequence_accumulator>
            35
        </sequence_accumulator>
        <sequence_accumulator>
            34
        </sequence_accumulator>
        <sequence_accumulator>
            42
        </sequence_accumulator>
        <sequence_accumulator>
            40
        </sequence_accumulator>
        <sequence_accumulator>
            104
        </sequence_accumulator>
        <sequence_accumulator>
            72
        </sequence_accumulator>
        <sequence_accumulator>
            73
        </sequence_accumulator>
        <sequence_accumulator>
            65
        </sequence_accumulator>
        <sequence_accumulator>
            67
        </sequence_accumulator>
        <sequence_accumulator>
            66
        </sequence_accumulator>
        <sequence_accumulator>
            70
        </sequence_accumulator>
        <sequence_accumulator>
            68
        </sequence_accumulator>
        <sequence_accumulator>
            84
        </sequence_accumulator>
        <sequence_accumulator>
            80
        </sequence_accumulator>
        <sequence_accumulator>
            208
        </sequence_accumulator>
        <sequence_accumulator>
            144
        </sequence_accumulator>
        <sequence_accumulator>
            152
        </sequence_accumulator>
        <sequence_accumulator>
            136
        </sequence_accumulator>
        <sequence_accumulator>
            168
        </sequence_accumulator>
        <sequence_accumulator>
            160
        </sequence_accumulator>
        <sequence_accumulator>
            161
        </sequence_accumulator>
        <sequence_accumulator>
            163
        </sequence_accumulator>
        <sequence_accumulator>
            162
        </sequence_accumulator>
        <sequence_accumulator>
            166
        </sequence_accumulator>
        <sequence_accumulator>
            38
        </sequence_accumulator>
        <sequence_accumulator>
            39
        </sequence_accumulator>
        <sequence_accumulator>
            7
        </sequence_accumulator>
        <sequence_accumulator>
            15
        </sequence_accumulator>
        <sequence_accumulator>
            14
        </sequence_accumulator>
        <sequence_accumulator>
            30
        </sequence_accumulator>
        <sequence_accumulator>
            22
        </sequence_accumulator>
        <sequence_accumulator>
            54
        </sequence_accumulator>
        <sequence_accumulator>
            50
        </sequence_accumulator>
        <sequence_accumulator>
            51
        </sequence_accumulator>
        <sequence_accumulator>
            49
        </sequence_accumulator>
        <sequence_accumulator>
            57
        </sequence_accumulator>
        <sequence_accumulator>
            25
        </sequence_accumulator>
        <sequence_accumulator>
            29
        </sequence_accumulator>
        <sequence_accumulator>
            28
        </sequence_accumulator>
        <sequence_accumulator>
            60
        </sequence_accumulator>
        <sequence_accumulator>
            44
        </sequence_accumulator>
        <sequence_accumulator>
            45
        </sequence_accumulator>
        <sequence_accumulator>
            41
        </sequence_accumulator>
        <sequence_accumulator>
            105
        </sequence_accumulator>
        <sequence_accumulator>
            97
        </sequence_accumulator>
        <sequence_accumulator>
            99
        </sequence_accumulator>
        <sequence_accumulator>
            98
        </sequence_accumulator>
        <sequence_accumulator>
            102
        </sequence_accumulator>
        <sequence_accumulator>
            100
        </sequence_accumulator>
        <sequence_accumulator>
            101
        </sequence_accumulator>
        <sequence_accumulator>
            69
        </sequence_accumulator>
        <sequence_accumulator>
            77
        </sequence_accumulator>
        <sequence_accumulator>
            76
        </sequence_accumulator>
        <sequence_accumulator>
            78
        </sequence_accumulator>
        <sequence_accumulator>
            74
        </sequence_accumulator>
        <sequence_accumulator>
            90
        </sequence_accumulator>
        <sequence_accumulator>
            82
        </sequence_accumulator>
        <sequence_accumulator>
            83
        </sequence_accumulator>
        <sequence_accumulator>
            81
        </sequence_accumulator>
        <sequence_accumulator>
            89
        </sequence_accumulator>
        <sequence_accumulator>
            88
        </sequence_accumulator>
        <sequence_accumulator>
            120
        </sequence_accumulator>
        <sequence_accumulator>
            56
        </sequence_accumulator>
        <sequence_accumulator>
            184
        </sequence_accumulator>
        <sequence_accumulator>
            176
        </sequence_accumulator>
        <sequence_accumulator>
            177
        </sequence_accumulator>
        <sequence_accumulator>
            145
        </sequence_accumulator>
        <sequence_accumulator>
            147
        </sequence_accumulator>
        <sequence_accumulator>
            146
        </sequence_accumulator>
        <sequence_accumulator>
            150
        </sequence_accumulator>
        <sequence_accumulator>
            148
        </sequence_accumulator>
        <sequence_accumulator>
            156
        </sequence_accumulator>
        <sequence_accumulator>
            140
        </sequence_accumulator>
        <sequence_accumulator>
            172
        </sequence_accumulator>
        <sequence_accumulator>
            164
        </sequence_accumulator>
        <sequence_accumulator>
            228
        </sequence_accumulator>
        <sequence_accumulator>
            196
        </sequence_accumulator>
        <sequence_accumulator>
            197
        </sequence_accumulator>
        <sequence_accumulator>
            193
        </sequence_accumulator>
        <sequence_accumulator>
            195
        </sequence_accumulator>
        <sequence_accumulator>
            194
        </sequence_accumulator>
        <sequence_accumulator>
            202
        </sequence_accumulator>
        <sequence_accumulator>
            138
        </sequence_accumulator>
        <sequence_accumulator>
            139
        </sequence_accumulator>
        <sequence_accumulator>
            137
        </sequence_accumulator>
        <sequence_accumulator>
            201
        </sequence_accumulator>
        <sequence_accumulator>
            200
        </sequence_accumulator>
        <sequence_accumulator>
            232
        </sequence_accumulator>
        <sequence_accumulator>
            224
        </sequence_accumulator>
        <sequence_accumulator>
            240
        </sequence_accumulator>
        <sequence_accumulator>
            112
        </sequence_accumulator>
        <sequence_accumulator>
            113
        </sequence_accumulator>
        <sequence_accumulator>
            115
        </sequence_accumulator>
        <sequence_accumulator>
            114
        </sequence_accumulator>
        <sequence_accumulator>
            118
        </sequence_accumulator>
        <sequence_accumulator>
            86
        </sequence_accumulator>
        <sequence_accumulator>
            87
        </sequence_accumulator>
        <sequence_accumulator>
            23
        </sequence_accumulator>
        <sequence_accumulator>
            31
        </sequence_accumulator>
        <sequence_accumulator>
            27
        </sequence_accumulator>
        <sequence_accumulator>
            59
        </sequence_accumulator>
        <sequence_accumulator>
            43
        </sequence_accumulator>
        <sequence_accumulator>
            47
        </sequence_accumulator>
        <sequence_accumulator>
            46
        </sequence_accumulator>
        <sequence_accumulator>
            62
        </sequence_accumulator>
        <sequence_accumulator>
            58
        </sequence_accumulator>
        <sequence_accumulator>
            122
        </sequence_accumulator>
        <sequence_accumulator>
            106
        </sequence_accumulator>
        <sequence_accumulator>
            107
        </sequence_accumulator>
        <sequence_accumulator>
            75
        </sequence_accumulator>
        <sequence_accumulator>
            79
        </sequence_accumulator>
        <sequence_accumulator>
            71
        </sequence_accumulator>
        <sequence_accumulator>
            199
        </sequence_accumulator>
        <sequence_accumulator>
            135
        </sequence_accumulator>
        <sequence_accumulator>
            143
        </sequence_accumulator>
        <sequence_accumulator>
            141
        </sequence_accumulator>
        <sequence_accumulator>
            157
        </sequence_accumulator>
        <sequence_accumulator>
            149
        </sequence_accumulator>
        <sequence_accumulator>
            181
        </sequence_accumulator>
        <sequence_accumulator>
            53
        </sequence_accumulator>
        <sequence_accumulator>
            117
        </sequence_accumulator>
        <sequence_accumulator>
            85
        </sequence_accumulator>
        <sequence_accumulator>
            93
        </sequence_accumulator>
        <sequence_accumulator>
            92
        </sequence_accumulator>
        <sequence_accumulator>
            124
        </sequence_accumulator>
        <sequence_accumulator>
            116
        </sequence_accumulator>
        <sequence_accumulator>
            244
        </sequence_accumulator>
        <sequence_accumulator>
            180
        </sequence_accumulator>
        <sequence_accumulator>
            182
        </sequence_accumulator>
        <sequence_accumulator>
            178
        </sequence_accumulator>
        <sequence_accumulator>
            186
        </sequence_accumulator>
        <sequence_accumulator>
            154
        </sequence_accumulator>
        <sequence_accumulator>
            155
        </sequence_accumulator>
        <sequence_accumulator>
            153
        </sequence_accumulator>
        <sequence_accumulator>
            185
        </sequence_accumulator>
        <sequence_accumulator>
            169
        </sequence_accumulator>
        <sequence_accumulator>
            173
        </sequence_accumulator>
        <sequence_accumulator>
            165
        </sequence_accumulator>
        <sequence_accumulator>
            229
        </sequence_accumulator>
        <sequence_accumulator>
            225
        </sequence_accumulator>
        <sequence_accumulator>
            227
        </sequence_accumulator>
        <sequence_accumulator>
            226
        </sequence_accumulator>
        <sequence_accumulator>
            234
        </sequence_accumulator>
        <sequence_accumulator>
            170
        </sequence_accumulator>
        <sequence_accumulator>
            174
        </sequence_accumulator>
        <sequence_accumulator>
            142
        </sequence_accumulator>
        <sequence_accumulator>
            206
        </sequence_accumulator>
        <sequence_accumulator>
            198
        </sequence_accumulator>
        <sequence_accumulator>
            214
        </sequence_accumulator>
        <sequence_accumulator>
            210
        </sequence_accumulator>
        <sequence_accumulator>
            218
        </sequence_accumulator>
        <sequence_accumulator>
            216
        </sequence_accumulator>
        <sequence_accumulator>
            217
        </sequence_accumulator>
        <sequence_accumulator>
            209
        </sequence_accumulator>
        <sequence_accumulator>
            213
        </sequence_accumulator>
        <sequence_accumulator>
            212
        </sequence_accumulator>
        <sequence_accumulator>
            220
        </sequence_accumulator>
        <sequence_accumulator>
            204
        </sequence_accumulator>
        <sequence_accumulator>
            236
        </sequence_accumulator>
        <sequence_accumulator>
            108
        </sequence_accumulator>
        <sequence_accumulator>
            109
        </sequence_accumulator>
        <sequence_accumulator>
            237
        </sequence_accumulator>
        <sequence_accumulator>
            205
        </sequence_accumulator>
        <sequence_accumulator>
            207
        </sequence_accumulator>
        <sequence_accumulator>
            203
        </sequence_accumulator>
        <sequence_accumulator>
            235
        </sequence_accumulator>
        <sequence_accumulator>
            233
        </sequence_accumulator>
        <sequence_accumulator>
            249
        </sequence_accumulator>
        <sequence_accumulator>
            241
        </sequence_accumulator>
        <sequence_accumulator>
            243
        </sequence_accumulator>
        <sequence_accumulator>
            242
        </sequence_accumulator>
        <sequence_accumulator>
            250
        </sequence_accumulator>
        <sequence_accumulator>
            248
        </sequence_accumulator>
        <sequence_accumulator>
            252
        </sequence_accumulator>
        <sequence_accumulator>
            188
        </sequence_accumulator>
        <sequence_accumulator>
            189
        </sequence_accumulator>
        <sequence_accumulator>
            61
        </sequence_accumulator>
        <sequence_accumulator>
            125
        </sequence_accumulator>
        <sequence_accumulator>
            121
        </sequence_accumulator>
        <sequence_accumulator>
            123
        </sequence_accumulator>
        <sequence_accumulator>
            91
        </sequence_accumulator>
        <sequence_accumulator>
            219
        </sequence_accumulator>
        <sequence_accumulator>
            211
        </sequence_accumulator>
        <sequence_accumulator>
            215
        </sequence_accumulator>
        <sequence_accumulator>
            151
        </sequence_accumulator>
        <sequence_accumulator>
            159
        </sequence_accumulator>
        <sequence_accumulator>
            158
        </sequence_accumulator>
        <sequence_accumulator>
            222
        </sequence_accumulator>
        <sequence_accumulator>
            94
        </sequence_accumulator>
        <sequence_accumulator>
            126
        </sequence_accumulator>
        <sequence_accumulator>
            110
        </sequence_accumulator>
        <sequence_accumulator>
            111
        </sequence_accumulator>
        <sequence_accumulator>
            103
        </sequence_accumulator>
        <sequence_accumulator>
            119
        </sequence_accumulator>
        <sequence_accumulator>
            55
        </sequence_accumulator>
        <sequence_accumulator>
            183
        </sequence_accumulator>
        <sequence_accumulator>
            179
        </sequence_accumulator>
        <sequence_accumulator>
            187
        </sequence_accumulator>
        <sequence_accumulator>
            171
        </sequence_accumulator>
        <sequence_accumulator>
            175
        </sequence_accumulator>
        <sequence_accumulator>
            167
        </sequence_accumulator>
        <sequence_accumulator>
            231
        </sequence_accumulator>
        <sequence_accumulator>
            230
        </sequence_accumulator>
        <sequence_accumulator>
            246
        </sequence_accumulator>
        <sequence_accumulator>
            247
        </sequence_accumulator>
        <sequence_accumulator>
            245
        </sequence_accumulator>
        <sequence_accumulator>
            253
        </sequence_accumulator>
        <sequence_accumulator>
            221
        </sequence_accumulator>
        <sequence_accumulator>
            223
        </sequence_accumulator>
        <sequence_accumulator>
            95
        </sequence_accumulator>
        <sequence_accumulator>
            127
        </sequence_accumulator>
        <sequence_accumulator>
            63
        </sequence_accumulator>
        <sequence_accumulator>
            191
        </sequence_accumulator>
        <sequence_accumulator>
            190
        </sequence_accumulator>
        <sequence_accumulator>
            254
        </sequence_accumulator>
        <sequence_accumulator>
            238
        </sequence_accumulator>
        <sequence_accumulator>
            239
        </sequence_accumulator>
        <sequence_accumulator>
            255
        </sequence_accumulator>
        <sequence_accumulator>
            251
        </sequence_accumulator>
    </solution>
</checkpoint>
